adabox/__init__.py
adabox/plot_tools.py
adabox/proc.py
adabox/tools.py
adabox/files/__init__.py
adaptive_boxes-0.0.4.dist-info/LICENSE
adaptive_boxes-0.0.4.dist-info/METADATA
adaptive_boxes-0.0.4.dist-info/WHEEL
adaptive_boxes-0.0.4.dist-info/top_level.txt
adaptive_boxes-0.0.4.dist-info/RECORD
