Metadata-Version: 2.1
Name: adaptive-boxes
Version: 0.0.4
Summary: Python package for rectangular decomposition of 2D scenes/binary images
Home-page: https://github.com/jnfran92/adaptive-boxes
Author: Juan Francisco Chango
Author-email: jnfran92@gmail.com
License: UNKNOWN
Platform: UNKNOWN
Classifier: Programming Language :: Python :: 3
Classifier: License :: OSI Approved :: MIT License
Classifier: Intended Audience :: Science/Research
Classifier: Operating System :: OS Independent
Requires-Python: >=3.6
Requires-Dist: certifi (==2019.3.9)
Requires-Dist: cycler (==0.10.0)
Requires-Dist: kiwisolver (==1.1.0)
Requires-Dist: matplotlib (==3.1.1)
Requires-Dist: numpy (==1.17.1)
Requires-Dist: pandas (==0.25.1)
Requires-Dist: plyfile (==0.7)
Requires-Dist: pyparsing (==2.4.2)
Requires-Dist: python-dateutil (==2.8.0)
Requires-Dist: pytz (==2019.2)
Requires-Dist: scipy (==1.3.1)
Requires-Dist: six (==1.12.0)
